LICENSE
MANIFEST.in
README.md
setup.py
tap_twilio/__init__.py
tap_twilio/client.py
tap_twilio/discover.py
tap_twilio/schema.py
tap_twilio/streams.py
tap_twilio/sync.py
tap_twilio/transform.py
tap_twilio.egg-info/PKG-INFO
tap_twilio.egg-info/SOURCES.txt
tap_twilio.egg-info/dependency_links.txt
tap_twilio.egg-info/entry_points.txt
tap_twilio.egg-info/requires.txt
tap_twilio.egg-info/top_level.txt
tap_twilio/schemas/account_balance.json
tap_twilio/schemas/accounts.json
tap_twilio/schemas/addresses.json
tap_twilio/schemas/alerts.json
tap_twilio/schemas/applications.json
tap_twilio/schemas/available_phone_number_countries.json
tap_twilio/schemas/available_phone_numbers_local.json
tap_twilio/schemas/available_phone_numbers_mobile.json
tap_twilio/schemas/available_phone_numbers_toll_free.json
tap_twilio/schemas/calls.json
tap_twilio/schemas/conference_participants.json
tap_twilio/schemas/conferences.json
tap_twilio/schemas/dependent_phone_numbers.json
tap_twilio/schemas/incoming_phone_numbers.json
tap_twilio/schemas/keys.json
tap_twilio/schemas/message_media.json
tap_twilio/schemas/messages.json
tap_twilio/schemas/outgoing_caller_ids.json
tap_twilio/schemas/queues.json
tap_twilio/schemas/recordings.json
tap_twilio/schemas/transcriptions.json
tap_twilio/schemas/usage_records.json
tap_twilio/schemas/usage_triggers.json
tests/test_all_fields.py
tests/test_automatic_fields.py
tests/test_bookmarks.py
tests/test_discovery.py
tests/test_pagination.py
tests/test_start_date.py