Metadata-Version: 2.4
Name: tap-twilio
Version: 0.2.0
Summary: Singer.io tap for extracting data from the Twilio API
Author: jeff.huth@bytecode.io
Classifier: Programming Language :: Python :: 3 :: Only
License-File: LICENSE
Requires-Dist: backoff==1.8.0
Requires-Dist: requests==2.32.3
Requires-Dist: singer-python==5.13.0
Dynamic: author
Dynamic: classifier
Dynamic: license-file
Dynamic: requires-dist
Dynamic: summary
